outputs/__init__.py
outputs/json_output.py
outputs/markdown_output.py
outputs/yaml_output.py
tasks/__init__.py
tasks/check_custom_roles.py
tasks/check_namespace_isolation.py
tasks/check_network_policies.py
tasks/check_password_auth.py
tasks/check_privileged_containers.py
tasks/check_rbac.py
tasks/check_versions.py
tasks/utils.py
kubesleuth-0.1.1.dist-info/LICENSE
kubesleuth-0.1.1.dist-info/METADATA
kubesleuth-0.1.1.dist-info/WHEEL
kubesleuth-0.1.1.dist-info/entry_points.txt
kubesleuth-0.1.1.dist-info/top_level.txt
kubesleuth-0.1.1.dist-info/RECORD
