Metadata-Version: 2.1
Name: kubesleuth
Version: 0.1.1
Summary: A tool for auditing Kubernetes clusters for misconfigurations, security issues, and best practices.
Home-page: https://github.com/thevanguardian/kubesleuth
Author: Benjamin Cody Pate
Author-email: resume@epic-geek.net
License: GPLv3
Classifier: Development Status :: 4 - Beta
Classifier: Intended Audience :: Developers
Classifier: License :: OSI Approved :: GNU General Public License v3 (GPLv3)
Classifier: Programming Language :: Python :: 3.8
Classifier: Programming Language :: Python :: 3.9
Classifier: Programming Language :: Python :: 3.10
Classifier: Programming Language :: Python :: 3.11
Classifier: Topic :: Software Development :: Libraries :: Python Modules
Classifier: Topic :: System :: Systems Administration
Classifier: Topic :: Utilities
Requires-Python: >=3.8
License-File: LICENSE
Requires-Dist: kubernetes (>=25.3.0)
Requires-Dist: jinja2 (>=3.1.2)
Requires-Dist: markdown2 (>=2.4.2)
Requires-Dist: requests (>=2.25.1)
Requires-Dist: pyyaml (>=5.4.1)
Requires-Dist: twine
